dvcw/__init__.py
dvcw/api.py
dvcw-0.0.1a0.dist-info/LICENSE
dvcw-0.0.1a0.dist-info/METADATA
dvcw-0.0.1a0.dist-info/WHEEL
dvcw-0.0.1a0.dist-info/top_level.txt
dvcw-0.0.1a0.dist-info/RECORD
